odoo/addons/ssi_bad_debt_direct_write_off/README.rst
odoo/addons/ssi_bad_debt_direct_write_off/__init__.py
odoo/addons/ssi_bad_debt_direct_write_off/__manifest__.py
odoo/addons/ssi_bad_debt_direct_write_off/data/account_journal_data.xml
odoo/addons/ssi_bad_debt_direct_write_off/data/approval_template_data.xml
odoo/addons/ssi_bad_debt_direct_write_off/data/ir_sequence_data.xml
odoo/addons/ssi_bad_debt_direct_write_off/data/policy_template_data.xml
odoo/addons/ssi_bad_debt_direct_write_off/data/sequence_template_data.xml
odoo/addons/ssi_bad_debt_direct_write_off/demo/account_account_demo.xml
odoo/addons/ssi_bad_debt_direct_write_off/demo/account_journal_demo.xml
odoo/addons/ssi_bad_debt_direct_write_off/demo/bad_debt_direct_write_off_type_demo.xml
odoo/addons/ssi_bad_debt_direct_write_off/models/__init__.py
odoo/addons/ssi_bad_debt_direct_write_off/models/bad_debt_direct_write_off.py
odoo/addons/ssi_bad_debt_direct_write_off/models/bad_debt_direct_write_off_detail.py
odoo/addons/ssi_bad_debt_direct_write_off/models/bad_debt_direct_write_off_type.py
odoo/addons/ssi_bad_debt_direct_write_off/security/ir.model.access.csv
odoo/addons/ssi_bad_debt_direct_write_off/security/ir_module_category_data.xml
odoo/addons/ssi_bad_debt_direct_write_off/security/ir_rule_data.xml
odoo/addons/ssi_bad_debt_direct_write_off/security/res_group_data.xml
odoo/addons/ssi_bad_debt_direct_write_off/static/description/icon.png
odoo/addons/ssi_bad_debt_direct_write_off/views/bad_debt_direct_write_off_detail_view.xml
odoo/addons/ssi_bad_debt_direct_write_off/views/bad_debt_direct_write_off_type_view.xml
odoo/addons/ssi_bad_debt_direct_write_off/views/bad_debt_direct_write_off_view.xml
odoo14_addon_ssi_bad_debt_direct_write_off-14.0.1.1.0.dist-info/METADATA
odoo14_addon_ssi_bad_debt_direct_write_off-14.0.1.1.0.dist-info/WHEEL
odoo14_addon_ssi_bad_debt_direct_write_off-14.0.1.1.0.dist-info/top_level.txt
odoo14_addon_ssi_bad_debt_direct_write_off-14.0.1.1.0.dist-info/RECORD
